[
  {
    "description": "",
    "elements": [
      {
        "description": "",
        "id": "contact-page-validation;verify-mandatory-field-validation-messages-are-displayed-and-cleared",
        "keyword": "Scenario Outline",
        "line": 13,
        "name": "Verify mandatory field validation messages are displayed and cleared",
        "steps": [
          {
            "keyword": "Before",
            "hidden": true,
            "result": {
              "status": "passed",
              "duration": 516835500
            }
          },
          {
            "arguments": [],
            "keyword": "Given ",
            "line": 5,
            "name": "I navigate to the Contact page",
            "match": {
              "location": "features\\step-definitions\\contact.steps.ts:5"
            },
            "result": {
              "status": "passed",
              "duration": 1887086499
            }
          },
          {
            "arguments": [],
            "keyword": "When ",
            "line": 6,
            "name": "I click the Submit button",
            "match": {
              "location": "features\\step-definitions\\contact.steps.ts:12"
            },
            "result": {
              "status": "passed",
              "duration": 381598100
            }
          },
          {
            "arguments": [],
            "keyword": "Then ",
            "line": 7,
            "name": "I should see validation errors for mandatory fields",
            "match": {
              "location": "features\\step-definitions\\contact.steps.ts:17"
            },
            "result": {
              "status": "passed",
              "duration": 562054600
            }
          },
          {
            "arguments": [],
            "keyword": "When ",
            "line": 8,
            "name": "I enter valid contact details \"damodhar\" \"damodhar@gmail.com\" \"Mandatory fields entered\"",
            "match": {
              "location": "features\\step-definitions\\contact.steps.ts:22"
            },
            "result": {
              "status": "passed",
              "duration": 598285000
            }
          },
          {
            "arguments": [],
            "keyword": "Then ",
            "line": 9,
            "name": "all validation errors should be cleared",
            "match": {
              "location": "features\\step-definitions\\contact.steps.ts:28"
            },
            "result": {
              "status": "passed",
              "duration": 40517899
            }
          },
          {
            "keyword": "After",
            "hidden": true,
            "result": {
              "status": "passed",
              "duration": 555110200
            }
          }
        ],
        "tags": [
          {
            "name": "@TC1",
            "line": 3
          }
        ],
        "type": "scenario"
      },
      {
        "description": "",
        "id": "contact-page-validation;submit-contact-form-successfully",
        "keyword": "Scenario Outline",
        "line": 26,
        "name": "Submit contact form successfully",
        "steps": [
          {
            "keyword": "Before",
            "hidden": true,
            "result": {
              "status": "passed",
              "duration": 576264799
            }
          },
          {
            "arguments": [],
            "keyword": "Given ",
            "line": 19,
            "name": "I navigate to the Contact page",
            "match": {
              "location": "features\\step-definitions\\contact.steps.ts:5"
            },
            "result": {
              "status": "passed",
              "duration": 1847885800
            }
          },
          {
            "arguments": [],
            "keyword": "When ",
            "line": 20,
            "name": "I enter valid contact details \"damodhar\" \"damodhar@gmail.com\" \"Mandatory fields entered\"",
            "match": {
              "location": "features\\step-definitions\\contact.steps.ts:22"
            },
            "result": {
              "status": "passed",
              "duration": 817983600
            }
          },
          {
            "arguments": [],
            "keyword": "When ",
            "line": 21,
            "name": "I click the Submit button",
            "match": {
              "location": "features\\step-definitions\\contact.steps.ts:12"
            },
            "result": {
              "status": "passed",
              "duration": 49950100
            }
          },
          {
            "arguments": [],
            "keyword": "Then ",
            "line": 22,
            "name": "I should see a successful submission message",
            "match": {
              "location": "features\\step-definitions\\contact.steps.ts:33"
            },
            "result": {
              "status": "passed",
              "duration": 1430791099
            }
          },
          {
            "keyword": "After",
            "hidden": true,
            "result": {
              "status": "passed",
              "duration": 439450899
            }
          }
        ],
        "tags": [
          {
            "name": "@TC2",
            "line": 17
          }
        ],
        "type": "scenario"
      },
      {
        "description": "",
        "id": "contact-page-validation;submit-contact-form-successfully",
        "keyword": "Scenario Outline",
        "line": 27,
        "name": "Submit contact form successfully",
        "steps": [
          {
            "keyword": "Before",
            "hidden": true,
            "result": {
              "status": "passed",
              "duration": 568850399
            }
          },
          {
            "arguments": [],
            "keyword": "Given ",
            "line": 19,
            "name": "I navigate to the Contact page",
            "match": {
              "location": "features\\step-definitions\\contact.steps.ts:5"
            },
            "result": {
              "status": "passed",
              "duration": 1869401600
            }
          },
          {
            "arguments": [],
            "keyword": "When ",
            "line": 20,
            "name": "I enter valid contact details \"damodhar\" \"damodhar@gmail.com\" \"Mandatory fields entered\"",
            "match": {
              "location": "features\\step-definitions\\contact.steps.ts:22"
            },
            "result": {
              "status": "passed",
              "duration": 842925000
            }
          },
          {
            "arguments": [],
            "keyword": "When ",
            "line": 21,
            "name": "I click the Submit button",
            "match": {
              "location": "features\\step-definitions\\contact.steps.ts:12"
            },
            "result": {
              "status": "passed",
              "duration": 63524199
            }
          },
          {
            "arguments": [],
            "keyword": "Then ",
            "line": 22,
            "name": "I should see a successful submission message",
            "match": {
              "location": "features\\step-definitions\\contact.steps.ts:33"
            },
            "result": {
              "status": "passed",
              "duration": 1880555099
            }
          },
          {
            "keyword": "After",
            "hidden": true,
            "result": {
              "status": "passed",
              "duration": 497286799
            }
          }
        ],
        "tags": [
          {
            "name": "@TC2",
            "line": 17
          }
        ],
        "type": "scenario"
      },
      {
        "description": "",
        "id": "contact-page-validation;submit-contact-form-successfully",
        "keyword": "Scenario Outline",
        "line": 28,
        "name": "Submit contact form successfully",
        "steps": [
          {
            "keyword": "Before",
            "hidden": true,
            "result": {
              "status": "passed",
              "duration": 551684000
            }
          },
          {
            "arguments": [],
            "keyword": "Given ",
            "line": 19,
            "name": "I navigate to the Contact page",
            "match": {
              "location": "features\\step-definitions\\contact.steps.ts:5"
            },
            "result": {
              "status": "passed",
              "duration": 1846949599
            }
          },
          {
            "arguments": [],
            "keyword": "When ",
            "line": 20,
            "name": "I enter valid contact details \"damodhar\" \"damodhar@gmail.com\" \"Mandatory fields entered\"",
            "match": {
              "location": "features\\step-definitions\\contact.steps.ts:22"
            },
            "result": {
              "status": "passed",
              "duration": 795337700
            }
          },
          {
            "arguments": [],
            "keyword": "When ",
            "line": 21,
            "name": "I click the Submit button",
            "match": {
              "location": "features\\step-definitions\\contact.steps.ts:12"
            },
            "result": {
              "status": "passed",
              "duration": 65996500
            }
          },
          {
            "arguments": [],
            "keyword": "Then ",
            "line": 22,
            "name": "I should see a successful submission message",
            "match": {
              "location": "features\\step-definitions\\contact.steps.ts:33"
            },
            "result": {
              "status": "passed",
              "duration": 1897992000
            }
          },
          {
            "keyword": "After",
            "hidden": true,
            "result": {
              "status": "passed",
              "duration": 481218099
            }
          }
        ],
        "tags": [
          {
            "name": "@TC2",
            "line": 17
          }
        ],
        "type": "scenario"
      },
      {
        "description": "",
        "id": "contact-page-validation;submit-contact-form-successfully",
        "keyword": "Scenario Outline",
        "line": 29,
        "name": "Submit contact form successfully",
        "steps": [
          {
            "keyword": "Before",
            "hidden": true,
            "result": {
              "status": "passed",
              "duration": 529596799
            }
          },
          {
            "arguments": [],
            "keyword": "Given ",
            "line": 19,
            "name": "I navigate to the Contact page",
            "match": {
              "location": "features\\step-definitions\\contact.steps.ts:5"
            },
            "result": {
              "status": "passed",
              "duration": 1878001299
            }
          },
          {
            "arguments": [],
            "keyword": "When ",
            "line": 20,
            "name": "I enter valid contact details \"damodhar\" \"damodhar@gmail.com\" \"Mandatory fields entered\"",
            "match": {
              "location": "features\\step-definitions\\contact.steps.ts:22"
            },
            "result": {
              "status": "passed",
              "duration": 806951499
            }
          },
          {
            "arguments": [],
            "keyword": "When ",
            "line": 21,
            "name": "I click the Submit button",
            "match": {
              "location": "features\\step-definitions\\contact.steps.ts:12"
            },
            "result": {
              "status": "passed",
              "duration": 65884999
            }
          },
          {
            "arguments": [],
            "keyword": "Then ",
            "line": 22,
            "name": "I should see a successful submission message",
            "match": {
              "location": "features\\step-definitions\\contact.steps.ts:33"
            },
            "result": {
              "status": "passed",
              "duration": 1400398700
            }
          },
          {
            "keyword": "After",
            "hidden": true,
            "result": {
              "status": "passed",
              "duration": 476666499
            }
          }
        ],
        "tags": [
          {
            "name": "@TC2",
            "line": 17
          }
        ],
        "type": "scenario"
      },
      {
        "description": "",
        "id": "contact-page-validation;submit-contact-form-successfully",
        "keyword": "Scenario Outline",
        "line": 30,
        "name": "Submit contact form successfully",
        "steps": [
          {
            "keyword": "Before",
            "hidden": true,
            "result": {
              "status": "passed",
              "duration": 521931400
            }
          },
          {
            "arguments": [],
            "keyword": "Given ",
            "line": 19,
            "name": "I navigate to the Contact page",
            "match": {
              "location": "features\\step-definitions\\contact.steps.ts:5"
            },
            "result": {
              "status": "passed",
              "duration": 1822782799
            }
          },
          {
            "arguments": [],
            "keyword": "When ",
            "line": 20,
            "name": "I enter valid contact details \"damodhar\" \"damodhar@gmail.com\" \"Mandatory fields entered\"",
            "match": {
              "location": "features\\step-definitions\\contact.steps.ts:22"
            },
            "result": {
              "status": "passed",
              "duration": 828144799
            }
          },
          {
            "arguments": [],
            "keyword": "When ",
            "line": 21,
            "name": "I click the Submit button",
            "match": {
              "location": "features\\step-definitions\\contact.steps.ts:12"
            },
            "result": {
              "status": "passed",
              "duration": 58080200
            }
          },
          {
            "arguments": [],
            "keyword": "Then ",
            "line": 22,
            "name": "I should see a successful submission message",
            "match": {
              "location": "features\\step-definitions\\contact.steps.ts:33"
            },
            "result": {
              "status": "passed",
              "duration": 2429319900
            }
          },
          {
            "keyword": "After",
            "hidden": true,
            "result": {
              "status": "passed",
              "duration": 525842400
            }
          }
        ],
        "tags": [
          {
            "name": "@TC2",
            "line": 17
          }
        ],
        "type": "scenario"
      },
      {
        "description": "",
        "id": "contact-page-validation;verify-cart-calculations",
        "keyword": "Scenario",
        "line": 34,
        "name": "Verify cart calculations",
        "steps": [
          {
            "keyword": "Before",
            "hidden": true,
            "result": {
              "status": "passed",
              "duration": 490618199
            }
          },
          {
            "arguments": [],
            "keyword": "Given ",
            "line": 36,
            "name": "I navigate to the Shop page",
            "match": {
              "location": "features\\step-definitions\\Cart.steps.ts:10"
            },
            "result": {
              "status": "passed",
              "duration": 6914616199
            }
          },
          {
            "arguments": [],
            "keyword": "When ",
            "line": 38,
            "name": "I add 2 \"Stuffed Frog\" to the cart",
            "match": {
              "location": "features\\step-definitions\\Cart.steps.ts:20"
            },
            "result": {
              "status": "passed",
              "duration": 1138446100
            }
          },
          {
            "arguments": [],
            "keyword": "And ",
            "line": 39,
            "name": "I add 5 \"Fluffy Bunny\" to the cart",
            "match": {
              "location": "features\\step-definitions\\Cart.steps.ts:20"
            },
            "result": {
              "status": "passed",
              "duration": 1354021499
            }
          },
          {
            "arguments": [],
            "keyword": "And ",
            "line": 40,
            "name": "I add 3 \"Valentine Bear\" to the cart",
            "match": {
              "location": "features\\step-definitions\\Cart.steps.ts:20"
            },
            "result": {
              "status": "passed",
              "duration": 1203922800
            }
          },
          {
            "arguments": [],
            "keyword": "And ",
            "line": 42,
            "name": "I navigate to the Cart page",
            "match": {
              "location": "features\\step-definitions\\Cart.steps.ts:32"
            },
            "result": {
              "status": "passed",
              "duration": 5091277500
            }
          },
          {
            "arguments": [],
            "keyword": "Then ",
            "line": 44,
            "name": "the subtotal should equal unit price multiplied by quantity for each product",
            "match": {
              "location": "features\\step-definitions\\Cart.steps.ts:38"
            },
            "result": {
              "status": "passed",
              "duration": 140852100
            }
          },
          {
            "arguments": [],
            "keyword": "And ",
            "line": 46,
            "name": "the cart total should equal the sum of all subtotals",
            "match": {
              "location": "features\\step-definitions\\Cart.steps.ts:49"
            },
            "result": {
              "status": "passed",
              "duration": 185547200
            }
          },
          {
            "keyword": "After",
            "hidden": true,
            "result": {
              "status": "passed",
              "duration": 1229363199
            }
          }
        ],
        "tags": [
          {
            "name": "@TC3",
            "line": 33
          }
        ],
        "type": "scenario"
      }
    ],
    "id": "contact-page-validation",
    "line": 2,
    "keyword": "Feature",
    "name": "Contact Page Validation",
    "tags": [],
    "uri": "features\\contact.feature"
  }
]